bloomfilter/VERSION
bloomfilter/__init__.py
bloomfilter/bloomfilter.py
python_bloomfilter-0.0.2.dist-info/LICENSE
python_bloomfilter-0.0.2.dist-info/METADATA
python_bloomfilter-0.0.2.dist-info/WHEEL
python_bloomfilter-0.0.2.dist-info/top_level.txt
python_bloomfilter-0.0.2.dist-info/RECORD
