Metadata-Version: 2.1
Name: python-bloomfilter
Version: 0.0.2
Summary: Bloomfilter using numba to get performance close to C speed
Home-page: http://github.com/stevesimmons/bloomfilter
Author: Stephen Simmons
Author-email: mail@stevesimmons.com
License: MIT Licence
Platform: UNKNOWN
Classifier: License :: OSI Approved :: MIT License
Classifier: Programming Language :: Python
Classifier: Programming Language :: Python :: 3
Classifier: Programming Language :: Python :: 3.6
Classifier: Programming Language :: Python :: 3.7
Classifier: Programming Language :: Python :: 3.8
Requires-Python: >=3.6.0
Requires-Dist: numba
Requires-Dist: numpy
